activetune/__init__.py
activetune/api.py
activetune-0.0.9.dist-info/METADATA
activetune-0.0.9.dist-info/WHEEL
activetune-0.0.9.dist-info/top_level.txt
activetune-0.0.9.dist-info/RECORD
