Metadata-Version: 2.1
Name: activetune
Version: 0.0.9
Summary: Activetune Python SDK
Requires-Dist: requests
